bfsccylinder_models-0.2.34.data/data/LICENSE
bfsccylinder_models-0.2.34.data/data/README.md
bfsccylinder_models-0.2.34.dist-info/METADATA
bfsccylinder_models-0.2.34.dist-info/WHEEL
bfsccylinder_models-0.2.34.dist-info/RECORD
bfsccylinder_models-0.2.34.dist-info/LICENSE
bfsccylinder_models-0.2.34.dist-info/top_level.txt
bfsccylinder_models/koiter_cylinder.cpython-36m-x86_64-linux-gnu.so
bfsccylinder_models/koiter_cylinder_newton_raphson_sanders.py
bfsccylinder_models/__init__.py
bfsccylinder_models/koiter_cylinder_CTS_slow_sanders.py
bfsccylinder_models/version.py
bfsccylinder_models/koiter_cylinder_CTS.cpython-36m-x86_64-linux-gnu.so
bfsccylinder_models/koiter_cylinder_newton_raphson.py
bfsccylinder_models/linbuck_VAFW.cpython-36m-x86_64-linux-gnu.so
bfsccylinder_models/models.py
bfsccylinder_models/koiter_cylinder_CTS_slow.py
bfsccylinder_models/vatfunctions.py
bfsccylinder_models.libs/libgomp-f7e03b3e.so.1.0.0
