Metadata-Version: 2.1
Name: bfsccylinder-models
Version: 0.2.34
Summary: Models using the BFSCCylinder finite element
Home-page: https://github.com/saullocastro/bfsccylinder_models
Author: Saullo G. P. Castro
Author-email: S.G.P.Castro@tudelft.nl
License: 3-Clause BSD
Keywords: finite elements shell structural analysis buckling vibration dynamics
Platform: UNKNOWN
Classifier: Development Status :: 4 - Beta
Classifier: Intended Audience :: Education
Classifier: Intended Audience :: Science/Research
Classifier: Intended Audience :: Developers
Classifier: Topic :: Scientific/Engineering :: Mathematics
Classifier: Topic :: Education
Classifier: License :: OSI Approved :: BSD License
Classifier: Programming Language :: Python :: 3.6
Classifier: Programming Language :: Python :: 3.7
Classifier: Programming Language :: Python :: 3.8
Classifier: Programming Language :: Python :: 3.9
Classifier: Operating System :: Microsoft :: Windows
Classifier: Operating System :: Unix
Requires-Dist: bfsccylinder
Requires-Dist: numpy
Requires-Dist: scipy
Requires-Dist: composites
